LingJichuXueQt4BianchengFix1/README.md
LingJichuXueQt4BianchengFix1/__init__.py
LingJichuXueQt4BianchengFix1/__main__.py
LingJichuXueQt4BianchengFix1/file.epub
LingJichuXueQt4BianchengFix1/index.html
LingJichuXueQt4BianchengFix1/css/__init__.py
LingJichuXueQt4BianchengFix1/css/annotations.css
LingJichuXueQt4BianchengFix1/css/main.css
LingJichuXueQt4BianchengFix1/css/normalize.css
LingJichuXueQt4BianchengFix1/css/popup.css
LingJichuXueQt4BianchengFix1/font/__init__.py
LingJichuXueQt4BianchengFix1/font/fontello.eot
LingJichuXueQt4BianchengFix1/font/fontello.svg
LingJichuXueQt4BianchengFix1/font/fontello.ttf
LingJichuXueQt4BianchengFix1/font/fontello.woff
LingJichuXueQt4BianchengFix1/img/__init__.py
LingJichuXueQt4BianchengFix1/img/annotator-glyph-sprite.png
LingJichuXueQt4BianchengFix1/img/annotator-icon-sprite.png
LingJichuXueQt4BianchengFix1/img/apple-touch-icon.png
LingJichuXueQt4BianchengFix1/img/cancelfullscreen.png
LingJichuXueQt4BianchengFix1/img/close.png
LingJichuXueQt4BianchengFix1/img/fullscreen.png
LingJichuXueQt4BianchengFix1/img/loader.gif
LingJichuXueQt4BianchengFix1/img/menu-icon.png
LingJichuXueQt4BianchengFix1/img/save.png
LingJichuXueQt4BianchengFix1/img/saved.png
LingJichuXueQt4BianchengFix1/img/settings-s.png
LingJichuXueQt4BianchengFix1/img/settings.png
LingJichuXueQt4BianchengFix1/img/star.png
LingJichuXueQt4BianchengFix1/js/__init__.py
LingJichuXueQt4BianchengFix1/js/epub.js
LingJichuXueQt4BianchengFix1/js/epub.min.js
LingJichuXueQt4BianchengFix1/js/epub.min.map
LingJichuXueQt4BianchengFix1/js/hooks.min.js
LingJichuXueQt4BianchengFix1/js/hooks.min.map
LingJichuXueQt4BianchengFix1/js/reader.js
LingJichuXueQt4BianchengFix1/js/reader.js.map
LingJichuXueQt4BianchengFix1/js/reader.min.js
LingJichuXueQt4BianchengFix1/js/reader.min.map
LingJichuXueQt4BianchengFix1/js/hooks/__init__.py
LingJichuXueQt4BianchengFix1/js/hooks/extensions/__init__.py
LingJichuXueQt4BianchengFix1/js/hooks/extensions/highlight.js
ling_jichu_xue_qt4_biancheng_fix1-2024.3.2.0.dist-info/METADATA
ling_jichu_xue_qt4_biancheng_fix1-2024.3.2.0.dist-info/WHEEL
ling_jichu_xue_qt4_biancheng_fix1-2024.3.2.0.dist-info/entry_points.txt
ling_jichu_xue_qt4_biancheng_fix1-2024.3.2.0.dist-info/top_level.txt
ling_jichu_xue_qt4_biancheng_fix1-2024.3.2.0.dist-info/RECORD
